lustrius/__init__.py
lustrius-0.0.0.dist-info/METADATA
lustrius-0.0.0.dist-info/WHEEL
lustrius-0.0.0.dist-info/top_level.txt
lustrius-0.0.0.dist-info/RECORD
