Metadata-Version: 2.1
Name: lustrius
Version: 0.0.0
Summary: Coming soon
Author: Gregor Purdy
